exponential_counter/__about__.py
exponential_counter/__init__.py
exponential_counter-0.0.2.dist-info/METADATA
exponential_counter-0.0.2.dist-info/WHEEL
exponential_counter-0.0.2.dist-info/licenses/LICENSE
exponential_counter-0.0.2.dist-info/RECORD
