Metadata-Version: 2.1
Name: exponential-counter
Version: 0.0.2
Project-URL: Documentation, https://github.com/unknown/exponential-counter#readme
Project-URL: Issues, https://github.com/unknown/exponential-counter/issues
Project-URL: Source, https://github.com/unknown/exponential-counter
Author-email: Xiang Wang <ramwin@qq.com>
License-Expression: MIT
License-File: LICENSE
Classifier: Development Status :: 4 - Beta
Classifier: Programming Language :: Python
Classifier: Programming Language :: Python :: 3.7
Classifier: Programming Language :: Python :: 3.8
Classifier: Programming Language :: Python :: 3.9
Classifier: Programming Language :: Python :: 3.10
Classifier: Programming Language :: Python :: 3.11
Classifier: Programming Language :: Python :: Implementation :: CPython
Classifier: Programming Language :: Python :: Implementation :: PyPy
Requires-Python: >=3.7
